[
  {
    "question": "零",
    "answer1": "Linh",
    "answer2": "số 0"
  },
  {
    "question": "霊",
    "answer1": "Linh",
    "answer2": "linh hồn"
  },
  {
    "question": "裂",
    "answer1": "Liệt",
    "answer2": "rách nát"
  },
  {
    "question": "廉",
    "answer1": "Liêm",
    "answer2": "liêm chính"
  },
  {
    "question": "錬",
    "answer1": "Luyện",
    "answer2": "luyện kim"
  },
  {
    "question": "露",
    "answer1": "Lộ",
    "answer2": "sương, phơi bày"
  },
  {
    "question": "狼",
    "answer1": "Lang",
    "answer2": "sói"
  },
  {
    "question": "籠",
    "answer1": "Long",
    "answer2": "cái lồng"
  },
  {
    "question": "麓",
    "answer1": "Lộc",
    "answer2": "chân núi"
  },
  {
    "question": "倭",
    "answer1": "Woà",
    "answer2": "Nhật cổ"
  },
  {
    "question": "和",
    "answer1": "Hòa",
    "answer2": "ôn hòa"
  },
  {
    "question": "賄",
    "answer1": "Hối",
    "answer2": "hối lộ"
  },
  {
    "question": "惑",
    "answer1": "Hoặc",
    "answer2": "mê hoặc"
  },
  {
    "question": "枠",
    "answer1": "Khung",
    "answer2": "khung viền"
  },
  {
    "question": "湾",
    "answer1": "Loan",
    "answer2": "vịnh"
  },
  {
    "question": "腕",
    "answer1": "Oản",
    "answer2": "cánh tay"
  },
  {
    "question": "挨",
    "answer1": "Ải",
    "answer2": "chào hỏi"
  },
  {
    "question": "曖",
    "answer1": "Ái",
    "answer2": "mập mờ"
  },
  {
    "question": "握",
    "answer1": "Ác",
    "answer2": "nắm bắt"
  },
  {
    "question": "扱",
    "answer1": "Tráp",
    "answer2": "xử lý"
  },
  {
    "question": "宛",
    "answer1": "Uyển",
    "answer2": "gửi tới"
  },
  {
    "question": "嵐",
    "answer1": "Lam",
    "answer2": "bão tố"
  },
  {
    "question": "庵",
    "answer1": "Am",
    "answer2": "am tự"
  },
  {
    "question": "飴",
    "answer1": "Di",
    "answer2": "kẹo"
  },
  {
    "question": "逸",
    "answer1": "Dật",
    "answer2": "thoát ra"
  }
]